fc_xd_bigdata.py
fc_yuchen-2.0.dist-info/METADATA
fc_yuchen-2.0.dist-info/WHEEL
fc_yuchen-2.0.dist-info/top_level.txt
fc_yuchen-2.0.dist-info/RECORD
